{
  "version": 1,
  "active": false,
  "skill": "ralplan",
  "keyword": "$ralplan",
  "phase": "architect_iterate_revising_plan",
  "activated_at": "2026-05-06T23:22:45.527Z",
  "updated_at": "2026-05-07T01:25:57.352Z",
  "source": "keyword-detector",
  "session_id": "019dff33-adbb-7983-8e67-ee13ae07893b",
  "turn_id": "019dff99-d4f4-7613-9bb9-cec1a57da56a",
  "active_skills": [],
  "transition_message": "mode transiting: deep-interview -> ralplan",
  "transition_messages": [
    "mode transiting: deep-interview -> ralplan"
  ],
  "input_lock": {
    "active": false,
    "scope": "deep-interview-auto-approval",
    "acquired_at": "2026-05-06T15:01:42.918Z",
    "released_at": "2026-05-06T23:22:45.527Z",
    "blocked_inputs": [
      "yes",
      "y",
      "proceed",
      "continue",
      "ok",
      "sure",
      "go ahead",
      "next i should"
    ],
    "message": "Deep interview is active; auto-approval shortcuts are blocked until the interview finishes.",
    "exit_reason": "handoff"
  },
  "initialized_mode": "ralplan",
  "initialized_state_path": ".omx/state/sessions/019dff33-adbb-7983-8e67-ee13ae07893b/ralplan-state.json"
}